editdistance-stubs/METADATA.toml
editdistance-stubs/__init__.pyi
editdistance-stubs/py.typed
types_editdistance-0.8.0.20241221.dist-info/LICENSE
types_editdistance-0.8.0.20241221.dist-info/METADATA
types_editdistance-0.8.0.20241221.dist-info/WHEEL
types_editdistance-0.8.0.20241221.dist-info/top_level.txt
types_editdistance-0.8.0.20241221.dist-info/RECORD
